{
  "products": [
    {
      "_id": "1",
      "title": "اکسسوری",
      "img": "/myimages/SaatChubi315$.png",
      "description": "ساعت چوبی",
      "price": 19,
      "availableSizes": []
    },
    {
        "_id": "2",
        "title": "اکسسوری",
        "img": "/myimages/setGoldanJaghalami_95+47$.png",
        "description": "ست گلدان جا قلمی",
        "price": 29,
        "availableSizes": []
      },
      {
        "_id": "3",
        "title": "اکسسوری",
        "img": "/myimages/dastband300$.png",
        "description": "دستبند",
        "price": 12,
        "availableSizes": []
      },
      {
        "_id": "4",
        "title": "اکسسوری",
        "img": "/myimages/gardanband_700$.png",
        "description": "گردنبند",
        "price": 12,
        "availableSizes": []
      },
      {
        "_id": "5",
        "title": "اکسسوری",
        "img": "/myimages/saat_200$.png",
        "description": "ساعت",
        "price": 15,
        "availableSizes": []
      },
      {
        "_id": "6",
        "title": "اکسسوری",
        "img": "/myimages/traditionalPhone_970$.png",
        "description": "تلفن قدیمی",
        "price": 21,
        "availableSizes": []
      },
      {
        "_id": "7",
        "title": "اکسسوری",
        "img": "/myimages/jaSameOood_290$.png",
        "description": "جاشمعی و عود",
        "price": 35,
        "availableSizes": []
      },
      {
        "_id": "8",
        "title": "اکسسوری",
        "img": "/myimages/AyneGhaddi_400$.png",
        "description": "آینه قدی",
        "price": 56,
        "availableSizes": []
      }
  ]
}
